CHANGELOG
LICENSE
MANIFEST.in
WAIVER
WAIVER.asc
requirements.txt
setup.cfg
setup.py
test_requirements.txt
eth_erc712/__init__.py
eth_erc712/base.py
eth_erc712.egg-info/PKG-INFO
eth_erc712.egg-info/SOURCES.txt
eth_erc712.egg-info/dependency_links.txt
eth_erc712.egg-info/requires.txt
eth_erc712.egg-info/top_level.txt
eth_erc712/data/ERC712Example.bin
eth_erc712/data/ERC712Example.json
eth_erc712/data/ERC712Example.metadata.json
eth_erc712/unittest/__init__.py
eth_erc712/unittest/base.py
tests/test_basic.py