Metadata-Version: 2.1
Name: eth-erc712
Version: 0.0.1
Summary: ERC712 typed data sign material builder
Home-page: https://git.defalsify.org/eth-erc712
Author: Louis Holbrook
Author-email: dev@holbrook.no
License: AGPLv3+
Keywords: dlt,ethereum,token,blockchain,cryptocurrency
Classifier: Programming Language :: Python :: 3
Classifier: Operating System :: OS Independent
Classifier: Development Status :: 4 - Beta
Classifier: Environment :: Console
Classifier: Intended Audience :: Developers
Classifier: License :: OSI Approved :: GNU Affero General Public License v3 or later (AGPLv3+)
Classifier: Topic :: Internet
Classifier: Topic :: Software Development :: Libraries
Requires-Python: >=3.8
License-File: LICENSE
